pyvirtualserial/__init__.py
pyvirtualserial/virtual_serial.py
pyvirtualserial/bases/linux_virtual_serial.py
pyvirtualserial/bases/window_virtual_serial.py
pyvirtualserial/utils/com0com.py
pyvirtualserial/utils/context_managers.py
pyvirtualserial-1.1.0.dist-info/LICENSE.txt
pyvirtualserial-1.1.0.dist-info/METADATA
pyvirtualserial-1.1.0.dist-info/WHEEL
pyvirtualserial-1.1.0.dist-info/top_level.txt
pyvirtualserial-1.1.0.dist-info/RECORD
