Metadata-Version: 2.1
Name: pyvirtualserial
Version: 1.1.0
Summary: Library to create virtual serial ports on Windows and Linux.
Home-page: https://github.com/byrondelgithub/PyVirtualSerial
Author: byrondelgithub
Author-email: rhurtado5c@gmail.com
License: MIT
Project-URL: Documentation, https://pyscaffold.org/
Project-URL: Source, https://github.com/byrondelgithub/PyVirtualSerial
Platform: Windows
Platform: Linux
Classifier: Development Status :: 4 - Beta
Classifier: Programming Language :: Python
License-File: LICENSE.txt
Requires-Dist: loguru
Requires-Dist: pyserial
Requires-Dist: importlib-metadata ; python_version < "3.8"
Provides-Extra: testing
Requires-Dist: setuptools ; extra == 'testing'
Requires-Dist: pytest ; extra == 'testing'
Requires-Dist: pytest-cov ; extra == 'testing'
